{
  "client_documentation": "https://googleapis.dev/nodejs/billing/latest/index.html",
  "api_id": "cloudbilling.googleapis.com",
  "distribution_name": "@google-cloud/billing",
  "release_level": "ga",
  "default_version": "v1",
  "language": "nodejs",
  "name_pretty": "Cloud Billing",
  "repo": "googleapis/nodejs-billing",
  "product_documentation": "https://cloud.google.com/billing/docs",
  "requires_billing": true,
  "name": "billing",
  "issue_tracker": "https://issuetracker.google.com/savedsearches/559770"
}
